ahk_wmutil/__init__.py
ahk_wmutil/py.typed
ahk_wmutil-0.1.0.dist-info/LICENSE
ahk_wmutil-0.1.0.dist-info/METADATA
ahk_wmutil-0.1.0.dist-info/WHEEL
ahk_wmutil-0.1.0.dist-info/top_level.txt
ahk_wmutil-0.1.0.dist-info/RECORD
