Metadata-Version: 2.1
Name: ahk-wmutil
Version: 0.1.0
Summary: A Python AHK extension providing monitor functionality
Home-page: https://github.com/spyoungtech/ahk-wmutil
Author: Spencer Young
Author-email: spencer.young@spyoung.com
Project-URL: Documentation, https://github.com/spyoungtech/ahk-wmutil
Project-URL: Funding, https://github.com/sponsors/spyoungtech/
Project-URL: Source, https://github.com/spyoungtech/ahk-wmutil
Project-URL: Tracker, https://github.com/spyoungtech/ahk-wmutil/issues
Keywords: ahk,autohotkey,windows,mouse,keyboard,automation,pyautogui,wmutil,screeninfo
Classifier: Intended Audience :: Developers
Classifier: Topic :: Desktop Environment
Classifier: Programming Language :: Python
Classifier: Environment :: Win32 (MS Windows)
Classifier: License :: OSI Approved :: MIT License
Classifier: Operating System :: Microsoft :: Windows
Classifier: Programming Language :: Python :: 3 :: Only
Classifier: Programming Language :: Python :: 3.8
Classifier: Programming Language :: Python :: 3.9
Classifier: Programming Language :: Python :: 3.10
Classifier: Programming Language :: Python :: 3.11
Classifier: Programming Language :: Python :: 3.12
Classifier: Typing :: Typed
Requires-Python: >=3.8.0
License-File: LICENSE
Requires-Dist: wmutil
Requires-Dist: ahk >=1.7.8
